darklock/__init__.py
darklock/log_disc_writer.py
darklock/no_internet_socket.py
darklock/restrict_network_access.py
darklock/restrict_os_access.py
darklock/singleton.py
darklock-0.1.6.dist-info/LICENSE
darklock-0.1.6.dist-info/METADATA
darklock-0.1.6.dist-info/WHEEL
darklock-0.1.6.dist-info/top_level.txt
darklock-0.1.6.dist-info/RECORD
