Metadata-Version: 2.1
Name: darklock
Version: 0.1.6
Home-page: https://github.com/Capsize-Games/darklock
Author: Capsize LLC
Author-email: contact@capsizegames.com
License: GPL-3.0
Requires-Python: >=3.10.0
License-File: LICENSE
